wantedpages/__init__.py
wantedpages/macro.py
TracWantedPages-0.6.0.dist-info/COPYING
TracWantedPages-0.6.0.dist-info/METADATA
TracWantedPages-0.6.0.dist-info/WHEEL
TracWantedPages-0.6.0.dist-info/entry_points.txt
TracWantedPages-0.6.0.dist-info/top_level.txt
TracWantedPages-0.6.0.dist-info/RECORD
