Metadata-Version: 2.1
Name: TracWantedPages
Version: 0.6.0
Summary: List all TracLinks non-existent wiki pages.
Home-page: https://trac-hacks.org/wiki/WantedPagesMacro
Author: Justin Francis
Author-email: jfrancis@justinfrancis.org
Maintainer: Geert Linders
Maintainer-email: glinders@dynamiccontrols.com
License: BSD 3-Clause
Platform: UNKNOWN
